fastlmi/__init__.py
fastlmi/application.py
fastlmi/auth.py
fastlmi/typing.py
fastlmi/utils.py
fastlmi/ai_plugin/__init__.py
fastlmi/ai_plugin/models.py
fastlmi-0.2.0.dist-info/METADATA
fastlmi-0.2.0.dist-info/WHEEL
fastlmi-0.2.0.dist-info/licenses/LICENSE
fastlmi-0.2.0.dist-info/RECORD
